check_distribution/__init__.py
check_distribution/check_distribution.py
check_distribution/version.py
check_distribution-1.2.0.dist-info/licenses/LICENSE
check_distribution-1.2.0.dist-info/METADATA
check_distribution-1.2.0.dist-info/WHEEL
check_distribution-1.2.0.dist-info/top_level.txt
check_distribution-1.2.0.dist-info/RECORD
